senserecord/__init__.py
senserecord/__main__.py
senserecord/cli/__init__.py
senserecord/core/__init__.py
senserecord/gui/__init__.py
senserecord/gui/widgets.py
senserecord/http/__init__.py
senserecord/http/static/favicon.ico
senserecord/http/static/redoc.standalone.js
senserecord/http/static/swagger-ui-bundle.js
senserecord/http/static/swagger-ui.css
senserecord/main.py
senserecord-0.1.4.dist-info/entry_points.txt
senserecord-0.1.4.dist-info/COPYING
senserecord-0.1.4.dist-info/WHEEL
senserecord-0.1.4.dist-info/METADATA
senserecord-0.1.4.dist-info/RECORD
