Metadata-Version: 2.1
Name: senserecord
Version: 0.1.4
Summary: A cross-platform application for saving data streams from biosensor hardware.
License: GPL-3.0-or-later
Keywords: biosensor,eeg,meg,recording,capture
Author: Link Swanson
Author-email: link@swanson.link
Requires-Python: >=3.7,<4.0
Classifier: Development Status :: 2 - Pre-Alpha
Classifier: Environment :: Console
Classifier: Environment :: X11 Applications :: Qt
Classifier: Intended Audience :: Science/Research
Classifier: License :: OSI Approved :: GNU General Public License v3 or later (GPLv3+)
Classifier: Programming Language :: Python :: 3
Classifier: Programming Language :: Python :: 3 :: Only
Classifier: Programming Language :: Python :: 3.7
Classifier: Programming Language :: Python :: 3.8
Classifier: Programming Language :: Python :: 3.9
Classifier: Topic :: Scientific/Engineering
Classifier: Typing :: Typed
Requires-Dist: PyYAML (>=5.3.1,<6.0.0)
Requires-Dist: QtAwesome (>=1.0.1,<2.0.0)
Requires-Dist: aiofiles (>=0.6.0,<0.7.0)
Requires-Dist: brainflow (>=3.8.1,<4.0.0)
Requires-Dist: fastapi (>=0.61.2,<0.62.0)
Requires-Dist: typer[all] (>=0.3.2,<0.4.0)
Requires-Dist: uvicorn (>=0.12.2,<0.13.0)
